byte/__init__.py
byte/collection.py
byte/model.py
byte/property.py
byte/registry.py
byte/types.py
byte/compilers/__init__.py
byte/compilers/operation.py
byte/compilers/core/__init__.py
byte/compilers/core/base.py
byte/core/__init__.py
byte/core/compat.py
byte/core/helpers/__init__.py
byte/core/helpers/object.py
byte/core/helpers/resolve.py
byte/core/helpers/validate.py
byte/core/models/__init__.py
byte/core/models/property.py
byte/core/models/expressions/__init__.py
byte/core/models/expressions/base.py
byte/core/models/expressions/proxy.py
byte/core/models/nodes/__init__.py
byte/core/models/nodes/base.py
byte/core/models/nodes/set.py
byte/core/models/operations/__init__.py
byte/core/models/operations/base.py
byte/core/models/operations/delete.py
byte/core/models/operations/insert.py
byte/core/models/operations/select.py
byte/core/models/operations/update.py
byte/core/models/task/__init__.py
byte/core/models/task/base.py
byte/core/models/task/simple.py
byte/core/models/task/stream.py
byte/core/models/threading/__init__.py
byte/core/models/threading/local.py
byte/core/models/threading/pool.py
byte/core/plugin/__init__.py
byte/core/plugin/base.py
byte/core/plugin/manager.py
byte/executors/__init__.py
byte/executors/core/__init__.py
byte/executors/core/base/__init__.py
byte/executors/core/base/database.py
byte/executors/core/base/executor.py
byte/executors/core/base/format.py
byte/executors/core/base/simple.py
byte/executors/core/models/__init__.py
byte/executors/core/models/revision.py
byte/executors/core/models/database/__init__.py
byte/executors/core/models/database/connection.py
byte/executors/core/models/database/cursor.py
byte/executors/core/models/database/transaction.py
byte/executors/file/__init__.py
byte/executors/file/main.py
byte/executors/file/revision.py
byte/executors/file/lock/__init__.py
byte/executors/file/lock/base.py
byte/executors/file/lock/msvcrt.py
byte/executors/file/lock/posix.py
byte-0.3.1.dist-info/DESCRIPTION.rst
byte-0.3.1.dist-info/METADATA
byte-0.3.1.dist-info/RECORD
byte-0.3.1.dist-info/WHEEL
byte-0.3.1.dist-info/metadata.json
byte-0.3.1.dist-info/pbr.json
byte-0.3.1.dist-info/top_level.txt
