Metadata-Version: 2.0
Name: byte
Version: 0.3.1
Summary: Modular data-model framework, and object-relational mapper
Home-page: https://github.com/fuzeman/byte
Author: Dean Gardiner
Author-email: me@dgardiner.net
License: MIT
Platform: UNKNOWN
Classifier: Development Status :: 3 - Alpha
Classifier: Intended Audience :: Developers
Classifier: License :: OSI Approved :: MIT License
Classifier: Operating System :: OS Independent
Classifier: Programming Language :: Python
Classifier: Programming Language :: Python :: 2
Classifier: Programming Language :: Python :: 2.6
Classifier: Programming Language :: Python :: 2.7
Classifier: Programming Language :: Python :: 3
Classifier: Programming Language :: Python :: 3.3
Classifier: Programming Language :: Python :: 3.4
Classifier: Programming Language :: Python :: 3.5
Classifier: Programming Language :: Python :: 3.6
Classifier: Programming Language :: Python :: Implementation :: CPython
Classifier: Programming Language :: Python :: Implementation :: PyPy
Classifier: Topic :: Software Development :: Libraries
Requires-Dist: arrow (>=0.10.0,<1.0.0)
Requires-Dist: pyparsing (>=2.2.0,<3.0.0)
Requires-Dist: six (>=1.10.0,<2.0.0)
